pet/__init__.py
pet/__main__.py
pet/classmodule.py
pet/funcmodule.py
pet/gps.py
P.E.T_build-1.5.dist-info/METADATA
P.E.T_build-1.5.dist-info/WHEEL
P.E.T_build-1.5.dist-info/entry_points.txt
P.E.T_build-1.5.dist-info/top_level.txt
P.E.T_build-1.5.dist-info/RECORD
