Metadata-Version: 2.1
Name: P.E.T-build
Version: 1.5
Summary: A python tool to edit image geolocation data.
Home-page: UNKNOWN
License: UNKNOWN
Keywords: python,photo,edit,metadata,exif,gps
Platform: UNKNOWN
Classifier: Development Status :: 5 - Production/Stable
Classifier: Programming Language :: Python :: 3
Classifier: Environment :: Console
Requires-Dist: requests
Requires-Dist: typer
Requires-Dist: rich
Requires-Dist: pyexiftool
Requires-Dist: pyfzf
